{
  "project": "meichen-pwa-preview",
  "brand": "Meichen Beauty AI",
  "type": "public_sanitized_preview",
  "repository": "aaaaa31255-prog/meichen-pwa-preview",
  "private_main_repository": "aaaaa31255-prog/Repository-name-meichen-miniprogram",
  "live_url": "https://aaaaa31255-prog.github.io/meichen-pwa-preview/",
  "pages": {
    "source": "Deploy from a branch",
    "branch": "main",
    "folder": "/ (root)",
    "https": true
  },
  "safety_boundary": {
    "real_customer_data": false,
    "secrets_or_tokens": false,
    "original_color_chart_pdfs": false,
    "original_training_videos": false,
    "private_project_hub_records": false,
    "full_private_business_rules": false,
    "real_camera_access": false,
    "local_customer_storage": false,
    "external_network_dependencies": false
  },
  "status": "mobile_acceptance_passed",
  "version": "public-preview-v2",
  "deployment_commit": "8a2dccc9db6ba5bdf8dc7c9dc0b14704864b8f21",
  "latest_fix_commit": "9c24f5056743e0003efc1006c5894422e1827603",
  "accepted_by_user": true,
  "accepted_scope": [
    "iphone_safari_layout",
    "top_safe_area",
    "bottom_navigation_8_tabs",
    "public_sanitized_demo_boundary"
  ],
  "next_stage": "prepare_private_repo_sync_instruction"
}
